{
  "queries": [
    {
      "searchId": 12,
      "shareId": "0x0000000000000000",
      "name": "Most Downloaded",
      "description": "Files sorted by number of downloads in the last 7 days."
    },
    {
      "searchId": 13,
      "shareId": "0x0000000000000000",
      "name": "Most Recommended",
      "description": "Files sorted by number of recommendations in the last 7 days."
    },
    {
      "searchId": 14,
      "shareId": "0x0000000000000000",
      "name": "Screenshots of You",
      "description": "Indulge your ego and view screenshots featuring the star of the show...you."
    }
  ]
}